README.md
setup.py
testreporter/__init__.py
testreporter/runner.py
testreporter.egg-info/PKG-INFO
testreporter.egg-info/SOURCES.txt
testreporter.egg-info/dependency_links.txt
testreporter.egg-info/top_level.txt