Metadata-Version: 2.1
Name: testreporter
Version: 0.1.0
Summary: Get pretty output for your Django unit tests
Home-page: https://gitlab.com/SchoolOrchestration/libs/dj-testreporter
Author: Christo Crampton
Author-email: christo@appointmentguru.co
License: UNKNOWN
Platform: UNKNOWN
Classifier: Programming Language :: Python :: 3
Classifier: Operating System :: OS Independent
